{
  "persona": {
    "Isabella Rodriguez": {
      "movement": [
        78,
        19
      ],
      "pronunciatio": "\ud83d\udc83",
      "description": "continuing to serve customers at the counter (1) Isabella is taking orders from customers at the counter) @ the Ville:Hobbs Cafe:cafe:behind the cafe counter",
      "chat": null
    },
    "Maria Lopez": {
      "movement": [
        126,
        54
      ],
      "pronunciatio": "\ud83d\udcda\ud83d\udc40",
      "description": "studying physics at Oak Hill College (reviewing her physics notes from the previous class) @ the Ville:Dorm for Oak Hill College:Maria Lopez's room:computer",
      "chat": null
    },
    "Klaus Mueller": {
      "movement": [
        131,
        46
      ],
      "pronunciatio": "\ud83d\udcaa",
      "description": "continuing to study in the Oak Hill College library (1) Klaus is reviewing his notes on sociology) @ the Ville:Dorm for Oak Hill College:Klaus Mueller's room:desk",
      "chat": null
    }
  },
  "meta": {
    "curr_time": "February 13, 2023, 10:11:30"
  }
}